{
    "key": "group_5b5b8c790937a",
    "title": "Portfolio Item Settings",
    "fields": [
        {
            "key": "field_5f461ac336683",
            "label": "Short Description",
            "name": "short_description",
            "type": "textarea",
            "instructions": "",
            "required": 0,
            "conditional_logic": 0,
            "wrapper": {
                "width": "",
                "class": "",
                "id": ""
            },
            "default_value": "",
            "placeholder": "",
            "maxlength": "",
            "rows": "",
            "new_lines": ""
        },
        {
            "key": "field_605b7f892a763",
            "label": "Video Link (popup)",
            "name": "video_link_popup",
            "type": "text",
            "instructions": "Url link to: local video or youtube video.",
            "required": 0,
            "conditional_logic": 0,
            "wrapper": {
                "width": "",
                "class": "",
                "id": ""
            },
            "default_value": "",
            "placeholder": "",
            "prepend": "",
            "append": "",
            "maxlength": ""
        }
    ],
    "location": [
        [
            {
                "param": "post_type",
                "operator": "==",
                "value": "portfolio"
            }
        ]
    ],
    "menu_order": 0,
    "position": "normal",
    "style": "default",
    "label_placement": "top",
    "instruction_placement": "label",
    "hide_on_screen": "",
    "active": true,
    "description": "",
    "modified": 1616611560
}